manuscript2slides/__init__.py
manuscript2slides/__main__.py
manuscript2slides/cli.py
manuscript2slides/gui.py
manuscript2slides/io.py
manuscript2slides/models.py
manuscript2slides/orchestrator.py
manuscript2slides/startup.py
manuscript2slides/templates.py
manuscript2slides/utils.py
manuscript2slides/annotations/__init__.py
manuscript2slides/annotations/apply_to_slides.py
manuscript2slides/annotations/extract.py
manuscript2slides/annotations/restore_from_slides.py
manuscript2slides/internals/__init__.py
manuscript2slides/internals/constants.py
manuscript2slides/internals/define_config.py
manuscript2slides/internals/logger.py
manuscript2slides/internals/manifest.py
manuscript2slides/internals/paths.py
manuscript2slides/internals/run_context.py
manuscript2slides/internals/scaffold.py
manuscript2slides/pipelines/__init__.py
manuscript2slides/pipelines/docx2pptx.py
manuscript2slides/pipelines/pptx2docx.py
manuscript2slides/processing/__init__.py
manuscript2slides/processing/chunking.py
manuscript2slides/processing/create_slides.py
manuscript2slides/processing/docx_xml.py
manuscript2slides/processing/formatting.py
manuscript2slides/processing/populate_docx.py
manuscript2slides/processing/run_processing.py
manuscript2slides/resources/_resources.md
manuscript2slides/resources/docx_template.docx
manuscript2slides/resources/pptx_template.pptx
manuscript2slides/resources/sample_doc.docx
manuscript2slides/resources/sample_slides_output.pptx
manuscript2slides/resources/scaffold_README.md
manuscript2slides-0.1.4.dist-info/licenses/LICENSE
manuscript2slides-0.1.4.dist-info/METADATA
manuscript2slides-0.1.4.dist-info/WHEEL
manuscript2slides-0.1.4.dist-info/entry_points.txt
manuscript2slides-0.1.4.dist-info/top_level.txt
manuscript2slides-0.1.4.dist-info/RECORD
