Metadata-Version: 2.4
Name: manuscript2slides
Version: 0.1.4
Summary: Convert Word documents to PowerPoint slides and back
Author: talosgl
License-Expression: MIT
Project-URL: Homepage, https://github.com/talosgl/manuscript2slides
Project-URL: Repository, https://github.com/talosgl/manuscript2slides
Project-URL: Issues, https://github.com/talosgl/manuscript2slides/issues
Project-URL: Documentation, https://github.com/talosgl/manuscript2slides/tree/main/docs
Keywords: docx,pptx,converter,powerpoint,word
Classifier: Development Status :: 4 - Beta
Classifier: Intended Audience :: End Users/Desktop
Classifier: Intended Audience :: Developers
Classifier: Topic :: Office/Business
Classifier: Topic :: Text Processing
Classifier: Topic :: Utilities
Classifier: Programming Language :: Python :: 3
Classifier: Programming Language :: Python :: 3.10
Classifier: Programming Language :: Python :: 3.11
Classifier: Programming Language :: Python :: 3.12
Classifier: Programming Language :: Python :: 3.13
Classifier: Programming Language :: Python :: 3 :: Only
Classifier: Operating System :: OS Independent
Classifier: Environment :: X11 Applications :: Qt
Classifier: Natural Language :: English
Requires-Python: >=3.10
License-File: LICENSE
Requires-Dist: python-docx<2.0,>=1.1.0
Requires-Dist: python-pptx<1.0,>=0.6.21
Requires-Dist: platformdirs<5.0,>=3.5
Requires-Dist: PySide6<7.0,>=6.5.0
Requires-Dist: tomli>=2.0.0; python_version < "3.11"
Requires-Dist: tomli-w<2.0,>=1.0.0
Provides-Extra: dev
Requires-Dist: pytest<9.0,>=7.0.0; extra == "dev"
Requires-Dist: pytest-cov<6.0,>=4.0.0; extra == "dev"
Requires-Dist: pytest-qt<5.0,>=4.0.0; extra == "dev"
Requires-Dist: tomli>=2.0.0; extra == "dev"
Requires-Dist: tomli-w>=1.0.0; extra == "dev"
Requires-Dist: mypy<2.0,>=1.0.0; extra == "dev"
Requires-Dist: ruff<1.0,>=0.1.0; extra == "dev"
Dynamic: license-file
